{
  "apiVersion": "dashboard.grafana.app/v1beta1",
  "kind": "Dashboard",
  "metadata": {
    "name": "user-engagement"
  },
  "spec": {
    "annotations": {
      "list": []
    },
    "editable": true,
    "fiscalYearStartMonth": 0,
    "graphTooltip": 1,
    "links": [],
    "panels": [
      {
        "datasource": {
          "type": "testdata",
          "uid": "-- Grafana --"
        },
        "fieldConfig": {
          "defaults": {
            "color": {
              "mode": "thresholds"
            },
            "mappings": [],
            "thresholds": {
              "mode": "absolute",
              "steps": [
                {
                  "color": "green",
                  "value": null
                },
                {
                  "color": "yellow",
                  "value": 15000
                },
                {
                  "color": "red",
                  "value": 25000
                }
              ]
            },
            "unit": "short"
          },
          "overrides": []
        },
        "gridPos": {
          "h": 8,
          "w": 6,
          "x": 0,
          "y": 0
        },
        "id": 1,
        "options": {
          "colorMode": "value",
          "graphMode": "area",
          "justifyMode": "auto",
          "orientation": "auto",
          "reduceOptions": {
            "values": false,
            "calcs": ["lastNotNull"],
            "fields": ""
          },
          "textMode": "auto"
        },
        "targets": [
          {
            "datasource": {
              "type": "testdata",
              "uid": "-- Grafana --"
            },
            "refId": "A",
            "scenarioId": "random_walk",
            "min": 12000,
            "max": 28000,
            "alias": "DAU"
          }
        ],
        "title": "Daily Active Users (DAU)",
        "type": "stat"
      },
      {
        "datasource": {
          "type": "testdata",
          "uid": "-- Grafana --"
        },
        "fieldConfig": {
          "defaults": {
            "color": {
              "mode": "thresholds"
            },
            "mappings": [],
            "thresholds": {
              "mode": "absolute",
              "steps": [
                {
                  "color": "green",
                  "value": null
                }
              ]
            },
            "unit": "short"
          },
          "overrides": []
        },
        "gridPos": {
          "h": 8,
          "w": 6,
          "x": 6,
          "y": 0
        },
        "id": 2,
        "options": {
          "colorMode": "value",
          "graphMode": "area",
          "justifyMode": "auto",
          "orientation": "auto",
          "reduceOptions": {
            "values": false,
            "calcs": ["lastNotNull"],
            "fields": ""
          },
          "textMode": "auto"
        },
        "targets": [
          {
            "datasource": {
              "type": "testdata",
              "uid": "-- Grafana --"
            },
            "refId": "A",
            "scenarioId": "random_walk",
            "min": 55000,
            "max": 85000,
            "alias": "MAU"
          }
        ],
        "title": "Monthly Active Users (MAU)",
        "type": "stat"
      },
      {
        "datasource": {
          "type": "testdata",
          "uid": "-- Grafana --"
        },
        "fieldConfig": {
          "defaults": {
            "color": {
              "mode": "thresholds"
            },
            "mappings": [],
            "max": 100,
            "min": 0,
            "thresholds": {
              "mode": "absolute",
              "steps": [
                {
                  "color": "red",
                  "value": null
                },
                {
                  "color": "yellow",
                  "value": 60
                },
                {
                  "color": "green",
                  "value": 75
                }
              ]
            },
            "unit": "percent"
          },
          "overrides": []
        },
        "gridPos": {
          "h": 8,
          "w": 6,
          "x": 12,
          "y": 0
        },
        "id": 3,
        "options": {
          "orientation": "auto",
          "reduceOptions": {
            "values": false,
            "calcs": ["lastNotNull"],
            "fields": ""
          },
          "showThresholdLabels": false,
          "showThresholdMarkers": true
        },
        "targets": [
          {
            "datasource": {
              "type": "testdata",
              "uid": "-- Grafana --"
            },
            "refId": "A",
            "scenarioId": "random_walk",
            "min": 55,
            "max": 85
          }
        ],
        "title": "30-Day Retention Rate",
        "type": "gauge"
      },
      {
        "datasource": {
          "type": "testdata",
          "uid": "-- Grafana --"
        },
        "fieldConfig": {
          "defaults": {
            "color": {
              "mode": "thresholds"
            },
            "mappings": [],
            "thresholds": {
              "mode": "absolute",
              "steps": [
                {
                  "color": "green",
                  "value": null
                }
              ]
            },
            "unit": "short"
          },
          "overrides": []
        },
        "gridPos": {
          "h": 8,
          "w": 6,
          "x": 18,
          "y": 0
        },
        "id": 4,
        "options": {
          "colorMode": "value",
          "graphMode": "area",
          "justifyMode": "auto",
          "orientation": "auto",
          "reduceOptions": {
            "values": false,
            "calcs": ["lastNotNull"],
            "fields": ""
          },
          "textMode": "auto"
        },
        "targets": [
          {
            "datasource": {
              "type": "testdata",
              "uid": "-- Grafana --"
            },
            "refId": "A",
            "scenarioId": "random_walk",
            "min": 1200,
            "max": 2500,
            "alias": "New Users"
          }
        ],
        "title": "New User Signups (Today)",
        "type": "stat"
      },
      {
        "datasource": {
          "type": "testdata",
          "uid": "-- Grafana --"
        },
        "fieldConfig": {
          "defaults": {
            "color": {
              "mode": "palette-classic"
            },
            "custom": {
              "axisCenteredZero": false,
              "axisColorMode": "text",
              "axisLabel": "",
              "axisPlacement": "auto",
              "barAlignment": 0,
              "drawStyle": "line",
              "fillOpacity": 20,
              "gradientMode": "opacity",
              "hideFrom": {
                "tooltip": false,
                "viz": false,
                "legend": false
              },
              "lineInterpolation": "smooth",
              "lineWidth": 2,
              "pointSize": 5,
              "scaleDistribution": {
                "type": "linear"
              },
              "showPoints": "never",
              "spanNulls": false,
              "stacking": {
                "group": "A",
                "mode": "none"
              },
              "thresholdsStyle": {
                "mode": "off"
              }
            },
            "mappings": [],
            "thresholds": {
              "mode": "absolute",
              "steps": [
                {
                  "color": "green",
                  "value": null
                }
              ]
            },
            "unit": "short"
          },
          "overrides": []
        },
        "gridPos": {
          "h": 9,
          "w": 12,
          "x": 0,
          "y": 8
        },
        "id": 5,
        "options": {
          "legend": {
            "calcs": ["mean", "max", "lastNotNull"],
            "displayMode": "table",
            "placement": "bottom",
            "showLegend": true
          },
          "tooltip": {
            "mode": "multi",
            "sort": "desc"
          }
        },
        "targets": [
          {
            "datasource": {
              "type": "testdata",
              "uid": "-- Grafana --"
            },
            "refId": "A",
            "scenarioId": "random_walk",
            "min": 12000,
            "max": 28000,
            "alias": "DAU"
          },
          {
            "datasource": {
              "type": "testdata",
              "uid": "-- Grafana --"
            },
            "refId": "B",
            "scenarioId": "random_walk",
            "min": 1200,
            "max": 2500,
            "alias": "New Signups"
          }
        ],
        "title": "User Growth Trend",
        "type": "timeseries"
      },
      {
        "datasource": {
          "type": "testdata",
          "uid": "-- Grafana --"
        },
        "fieldConfig": {
          "defaults": {
            "color": {
              "mode": "palette-classic"
            },
            "custom": {
              "axisCenteredZero": false,
              "axisColorMode": "text",
              "axisLabel": "",
              "axisPlacement": "auto",
              "barAlignment": 0,
              "drawStyle": "bars",
              "fillOpacity": 80,
              "gradientMode": "none",
              "hideFrom": {
                "tooltip": false,
                "viz": false,
                "legend": false
              },
              "lineInterpolation": "linear",
              "lineWidth": 1,
              "pointSize": 5,
              "scaleDistribution": {
                "type": "linear"
              },
              "showPoints": "never",
              "spanNulls": false,
              "stacking": {
                "group": "A",
                "mode": "none"
              },
              "thresholdsStyle": {
                "mode": "off"
              }
            },
            "mappings": [],
            "thresholds": {
              "mode": "absolute",
              "steps": [
                {
                  "color": "green",
                  "value": null
                }
              ]
            },
            "unit": "short"
          },
          "overrides": []
        },
        "gridPos": {
          "h": 9,
          "w": 12,
          "x": 12,
          "y": 8
        },
        "id": 6,
        "options": {
          "legend": {
            "calcs": ["mean", "max"],
            "displayMode": "table",
            "placement": "bottom",
            "showLegend": true
          },
          "tooltip": {
            "mode": "multi",
            "sort": "desc"
          }
        },
        "targets": [
          {
            "datasource": {
              "type": "testdata",
              "uid": "-- Grafana --"
            },
            "refId": "A",
            "scenarioId": "random_walk",
            "min": 3000,
            "max": 8000,
            "alias": "Search Feature"
          },
          {
            "datasource": {
              "type": "testdata",
              "uid": "-- Grafana --"
            },
            "refId": "B",
            "scenarioId": "random_walk",
            "min": 2500,
            "max": 6500,
            "alias": "Dashboard Feature"
          },
          {
            "datasource": {
              "type": "testdata",
              "uid": "-- Grafana --"
            },
            "refId": "C",
            "scenarioId": "random_walk",
            "min": 1500,
            "max": 4000,
            "alias": "Reports Feature"
          }
        ],
        "title": "Feature Usage by Users",
        "type": "timeseries"
      }
    ],
    "schemaVersion": 38,
    "style": "dark",
    "tags": ["business", "engagement", "users"],
    "templating": {
      "list": []
    },
    "time": {
      "from": "now-30d",
      "to": "now"
    },
    "timepicker": {},
    "timezone": "",
    "title": "User Engagement",
    "uid": "user-engagement",
    "version": 1,
    "weekStart": ""
  }
}
